newsworker/__init__.py
newsworker/consts.py
newsworker/extractor.py
newsworker/finder.py
newsworker/tagmapper.py
newsworker/tools.py
newsworker-1.0.1.dist-info/DESCRIPTION.rst
newsworker-1.0.1.dist-info/METADATA
newsworker-1.0.1.dist-info/RECORD
newsworker-1.0.1.dist-info/WHEEL
newsworker-1.0.1.dist-info/metadata.json
newsworker-1.0.1.dist-info/top_level.txt
