Metadata-Version: 2.0
Name: newsworker
Version: 1.0.1
Summary: Advanced news feeds extractor and finder library. Helps to automatically extract news from websites without RSS/ATOM feeds
Home-page: https://github.com/ivbeg/newsworker
Author: Ivan Begtin
Author-email: ivan@begtin.tech
License: BSD
Keywords: news parsing extraction feeds rss atom
Platform: UNKNOWN
Classifier: Development Status :: 5 - Production/Stable
Classifier: Intended Audience :: Developers
Classifier: License :: OSI Approved :: BSD License
Classifier: Natural Language :: English
Classifier: Programming Language :: Python :: 3
Classifier: Programming Language :: Python :: 3.3
Classifier: Programming Language :: Python :: 3.4
Classifier: Programming Language :: Python :: 3.5
Classifier: Programming Language :: Python :: 3.6
Classifier: Programming Language :: Python :: Implementation :: CPython
Classifier: Programming Language :: Python :: Implementation :: PyPy
Requires-Dist: pyparsing
Requires-Dist: lxml
Requires-Dist: bs4
Requires-Dist: qddate
